Metadata-Version: 1.1
Name: scrapbag
Version: 0.1.1
Summary: Scrapbag Python lib
Home-page: https://github.com/Datary/scrapbag
Author: Datary developers team
Author-email: support@datary.io
License: UNKNOWN
Download-URL: https://github.com/Datary/scrapbag
Keywords: scrapman,scrapbag,utils,datary,scrapping
Platform: UNKNOWN
Classifier: Programming Language :: Python :: 3
Classifier: Programming Language :: Python :: 3.3
Classifier: Programming Language :: Python :: 3.4
Classifier: Programming Language :: Python :: 3.5
